[{"status": "ZERO_RESULTS"}, {"copyright": "\u00a9 Google", "date": "2022-02", "location": {"lat": -1.387108508078229, "lng": 36.74763457182238}, "pano_id": "IeiLbDtzutoWcm-jtQMvLQ", "status": "OK", "_file": "gsv_1.jpg"}, {"status": "ZERO_RESULTS"}, {"status": "ZERO_RESULTS"}, {"status": "ZERO_RESULTS"}, {"status": "ZERO_RESULTS"}, {"copyright": "\u00a9 Google", "date": "2018-02", "location": {"lat": -1.387166355889361, "lng": 36.818097641791}, "pano_id": "GBQD7wpFLVxuf626NcpLsA", "status": "OK", "_file": "gsv_6.jpg"}, {"status": "ZERO_RESULTS"}, {"status": "ZERO_RESULTS"}, {"status": "ZERO_RESULTS"}, {"copyright": "\u00a9 Google", "date": "2021-07", "location": {"lat": -1.372587977812926, "lng": 36.73336640596332}, "pano_id": "QVOsdVjWwRbuZ8UuHXaHkQ", "status": "OK", "_file": "gsv_10.jpg"}, {"status": "ZERO_RESULTS"}, {"copyright": "\u00a9 Google", "date": "2022-02", "location": {"lat": -1.372817120751627, "lng": 36.76177939379158}, "pano_id": "7fLVdS_uW6eOctrHGaSCsw", "status": "OK", "_file": "gsv_12.jpg"}, {"status": "ZERO_RESULTS"}, {"status": "ZERO_RESULTS"}, {"status": "ZERO_RESULTS"}, {"status": "ZERO_RESULTS"}, {"copyright": "\u00a9 Google", "date": "2018-10", "location": {"lat": -1.372353217115803, "lng": 36.83242140796347}, "pano_id": "j4Kay8Xeh9nhIFUeFMEjWg", "status": "OK", "_file": "gsv_17.jpg"}, {"status": "ZERO_RESULTS"}, {"status": "ZERO_RESULTS"}, {"status": "ZERO_RESULTS"}, {"copyright": "\u00a9 Google", "date": "2022-02", "location": {"lat": -1.357600330225824, "lng": 36.74680977204071}, "pano_id": "TeaL3iSWrW6I0v5m43UPFQ", "status": "OK", "_file": "gsv_21.jpg"}, {"copyright": "\u00a9 Google", "date": "2022-02", "location": {"lat": -1.357173916879982, "lng": 36.76236143080656}, "pano_id": "IVtkkK9V-O_snRzh9nTSTw", "status": "OK", "_file": "gsv_22.jpg"}, {"status": "ZERO_RESULTS"}, {"status": "ZERO_RESULTS"}, {"status": "ZERO_RESULTS"}, {"status": "ZERO_RESULTS"}, {"status": "ZERO_RESULTS"}, {"status": "ZERO_RESULTS"}, {"status": "ZERO_RESULTS"}, {"status": "ZERO_RESULTS"}, {"status": "ZERO_RESULTS"}, {"copyright": "\u00a9 Google", "date": "2022-04", "location": {"lat": -1.342104939570941, "lng": 36.76175127832852}, "pano_id": "44ZINg6KpMt0-qXK3U0pJA", "status": "OK", "_file": "gsv_32.jpg"}, {"status": "ZERO_RESULTS"}, {"status": "ZERO_RESULTS"}, {"status": "ZERO_RESULTS"}, {"status": "ZERO_RESULTS"}, {"status": "ZERO_RESULTS"}, {"status": "ZERO_RESULTS"}, {"status": "ZERO_RESULTS"}, {"copyright": "\u00a9 Google", "date": "2021-07", "location": {"lat": -1.327272888985658, "lng": 36.73343302068189}, "pano_id": "zzdIMlVyVvZdrXh-lzZI7g", "status": "OK", "_file": "gsv_40.jpg"}, {"status": "ZERO_RESULTS"}, {"copyright": "\u00a9 Google", "date": "2021-07", "location": {"lat": -1.327362156955332, "lng": 36.76125892716049}, "pano_id": "j5Hw6WkBRax_JB_J6bRVmA", "status": "OK", "_file": "gsv_42.jpg"}, {"status": "ZERO_RESULTS"}, {"status": "ZERO_RESULTS"}, {"copyright": "\u00a9 Google", "date": "2021-07", "location": {"lat": -1.32752268629665, "lng": 36.80372826774415}, "pano_id": "gpt2H_5WalqG3tbpycNe4Q", "status": "OK", "_file": "gsv_45.jpg"}, {"status": "ZERO_RESULTS"}, {"status": "ZERO_RESULTS"}, {"copyright": "\u00a9 Google", "date": "2022-04", "location": {"lat": -1.327403194399589, "lng": 36.8465888000923}, "pano_id": "opKBr7f1dAWHaninMPC54Q", "status": "OK", "_file": "gsv_48.jpg"}, {"status": "ZERO_RESULTS"}, {"status": "ZERO_RESULTS"}, {"status": "ZERO_RESULTS"}, {"status": "ZERO_RESULTS"}, {"copyright": "\u00a9 Google", "date": "2022-04", "location": {"lat": -1.312589699225455, "lng": 36.77547389107434}, "pano_id": "bu_kKHFIHgHqEKdzpQdpeQ", "status": "OK", "_file": "gsv_53.jpg"}, {"status": "ZERO_RESULTS"}, {"status": "ZERO_RESULTS"}, {"status": "ZERO_RESULTS"}, {"status": "ZERO_RESULTS"}, {"status": "ZERO_RESULTS"}, {"status": "ZERO_RESULTS"}, {"status": "ZERO_RESULTS"}, {"copyright": "\u00a9 Google", "date": "2021-08", "location": {"lat": -1.297445179805448, "lng": 36.74758490813324}, "pano_id": "5vc2ENz3VZ2gSjtvNmHTMg", "status": "OK", "_file": "gsv_61.jpg"}, {"copyright": "\u00a9 Google", "date": "2021-07", "location": {"lat": -1.297306276666601, "lng": 36.76167367301841}, "pano_id": "fr9PfRJDymmFckOdI9cp8w", "status": "OK", "_file": "gsv_62.jpg"}, {"status": "ZERO_RESULTS"}, {"copyright": "\u00a9 Google", "date": "2021-09", "location": {"lat": -1.297455740491908, "lng": 36.78978038472593}, "pano_id": "vMFH3St2-ZJAXmFf2d4rGQ", "status": "OK", "_file": "gsv_64.jpg"}, {"copyright": "\u00a9 Google", "date": "2022-04", "location": {"lat": -1.297648644870348, "lng": 36.80420513653194}, "pano_id": "t1hVtDEs2US6xPbIFnwBhg", "status": "OK", "_file": "gsv_65.jpg"}, {"copyright": "\u00a9 Google", "date": "2021-09", "location": {"lat": -1.297575571728826, "lng": 36.81804087862314}, "pano_id": "T964UdC3qfNLvJLkcHLV5w", "status": "OK", "_file": "gsv_66.jpg"}, {"status": "ZERO_RESULTS"}, {"copyright": "\u00a9 Google", "date": "2021-08", "location": {"lat": -1.297682139408788, "lng": 36.84680853856887}, "pano_id": "48ASJee1twdKj4GAibc4ug", "status": "OK", "_file": "gsv_68.jpg"}, {"copyright": "\u00a9 Google", "date": "2022-04", "location": {"lat": -1.296914775043452, "lng": 36.86088488713548}, "pano_id": "xGV__A6IYhWyRNDZK7ozYQ", "status": "OK", "_file": "gsv_69.jpg"}, {"status": "ZERO_RESULTS"}, {"copyright": "\u00a9 Google", "date": "2021-07", "location": {"lat": -1.282841278467165, "lng": 36.74758992383846}, "pano_id": "3Gcdy2zcf2CZrotYX2Bfag", "status": "OK", "_file": "gsv_71.jpg"}, {"copyright": "\u00a9 Google", "date": "2021-07", "location": {"lat": -1.282200298913585, "lng": 36.76171675055227}, "pano_id": "djjUW1mY_wB_f5pdrhOTHQ", "status": "OK", "_file": "gsv_72.jpg"}, {"status": "ZERO_RESULTS"}, {"status": "ZERO_RESULTS"}, {"status": "ZERO_RESULTS"}, {"copyright": "\u00a9 Google", "date": "2021-08", "location": {"lat": -1.282502523432457, "lng": 36.8183120435219}, "pano_id": "zYjd97euRpBb_SPx4fSyrg", "status": "OK", "_file": "gsv_76.jpg"}, {"copyright": "\u00a9 Google", "date": "2022-03", "location": {"lat": -1.282235099355426, "lng": 36.83183731577589}, "pano_id": "jCl3DSh53f-Ng_5bp0m76g", "status": "OK", "_file": "gsv_77.jpg"}, {"copyright": "\u00a9 Google", "date": "2022-05", "location": {"lat": -1.282334792527362, "lng": 36.84679269048692}, "pano_id": "s5rd2IyLNPAQCtm-zT8Kxg", "status": "OK", "_file": "gsv_78.jpg"}, {"status": "ZERO_RESULTS"}, {"status": "ZERO_RESULTS"}, {"copyright": "\u00a9 Google", "date": "2018-02", "location": {"lat": -1.267624622357578, "lng": 36.74758277029157}, "pano_id": "VyTAXEYIMQ_djLAeMwLnpg", "status": "OK", "_file": "gsv_81.jpg"}, {"copyright": "\u00a9 Google", "date": "2022-04", "location": {"lat": -1.267354272123201, "lng": 36.76172916411178}, "pano_id": "mMkx_MluGDgFdbkCafBHwA", "status": "OK", "_file": "gsv_82.jpg"}, {"status": "ZERO_RESULTS"}, {"status": "ZERO_RESULTS"}, {"copyright": "\u00a9 Google", "date": "2022-04", "location": {"lat": -1.267362732380279, "lng": 36.80416652046273}, "pano_id": "tMLvwtTuOVWF4bgGmPm9uA", "status": "OK", "_file": "gsv_85.jpg"}, {"copyright": "\u00a9 Google", "date": "2022-04", "location": {"lat": -1.267480957995395, "lng": 36.81825191252457}, "pano_id": "Y3UcskBGaF5Uxb38m4Ay4A", "status": "OK", "_file": "gsv_86.jpg"}, {"copyright": "\u00a9 Google", "date": "2022-04", "location": {"lat": -1.267215012229242, "lng": 36.8323320717602}, "pano_id": "-kfGjGYlGRginLra-uerAQ", "status": "OK", "_file": "gsv_87.jpg"}, {"copyright": "\u00a9 Google", "date": "2021-09", "location": {"lat": -1.267385166498964, "lng": 36.84684787135857}, "pano_id": "7GLj0AfyYfO8KGPLhaGnjQ", "status": "OK", "_file": "gsv_88.jpg"}, {"status": "ZERO_RESULTS"}, {"copyright": "\u00a9 Google", "date": "2021-08", "location": {"lat": -1.252291023571938, "lng": 36.73338416989412}, "pano_id": "o9nu8ShqP8r233Eev9Tw8w", "status": "OK", "_file": "gsv_90.jpg"}, {"status": "ZERO_RESULTS"}, {"status": "ZERO_RESULTS"}, {"copyright": "\u00a9 Google", "date": "2022-05", "location": {"lat": -1.252433451701405, "lng": 36.77594650360282}, "pano_id": "CUhxNV6Gjd_usI-yjGYjsw", "status": "OK", "_file": "gsv_93.jpg"}, {"copyright": "\u00a9 Google", "date": "2022-02", "location": {"lat": -1.252471361796613, "lng": 36.78990373358916}, "pano_id": "roqQX4-2sOI0AazPVaNK3w", "status": "OK", "_file": "gsv_94.jpg"}, {"status": "ZERO_RESULTS"}, {"copyright": "\u00a9 Google", "date": "2022-04", "location": {"lat": -1.252132031429179, "lng": 36.81830423963839}, "pano_id": "6XOQxo3X1sfPwjdrEa_nHg", "status": "OK", "_file": "gsv_96.jpg"}, {"copyright": "\u00a9 Google", "date": "2021-07", "location": {"lat": -1.252521866570215, "lng": 36.83247629283343}, "pano_id": "3XFFodm8md99nveRYXe0eg", "status": "OK", "_file": "gsv_97.jpg"}, {"status": "ZERO_RESULTS"}, {"status": "ZERO_RESULTS"}]